wata/__init__.py
wata/console.py
wata/display/__init__.py
wata/display/display.py
wata/display/utils/__init__.py
wata/display/utils/utils.py
wata/file/__init__.py
wata/file/file.py
wata/file/utils/__init__.py
wata/file/utils/file_tree_utils.py
wata/file/utils/load_and_write_file.py
wata/file/utils/type_mapping.py
wata/file/utils/utils.py
wata/geo/__init__.py
wata/geo/geo.py
wata/geo/utils/__init__.py
wata/geo/utils/coord_trans.py
wata/geo/utils/utils.py
wata/image/__init__.py
wata/image/img.py
wata/image/utils/__init__.py
wata/image/utils/utils.py
wata/mathematics/__init__.py
wata/mathematics/mathematics.py
wata/mathematics/utils/__init__.py
wata/mathematics/utils/trans_coordinate.py
wata/mathematics/utils/utils.py
wata/pointcloud/__init__.py
wata/pointcloud/pcd.py
wata/pointcloud/ops/__init__.py
wata/pointcloud/ops/roiaware_pool3d/__init__.py
wata/pointcloud/ops/roiaware_pool3d/roiaware_pool3d_cuda.cpython-38-x86_64-linux-gnu.so
wata/pointcloud/ops/roiaware_pool3d/roiaware_pool3d_utils.py
wata/pointcloud/ops/roiaware_pool3d/src/roiaware_pool3d.cpp
wata/pointcloud/ops/roiaware_pool3d/src/roiaware_pool3d_kernel.cu
wata/pointcloud/utils/__init__.py
wata/pointcloud/utils/load_pcd.py
wata/pointcloud/utils/move_pcd.py
wata/pointcloud/utils/o3d_visualize_utils.py
wata/pointcloud/utils/plot_visualize_utils.py
wata/pointcloud/utils/qtopengl_visualize_utils.py
wata/pointcloud/utils/utils.py
wata/resources/__init__.py
wata/resources/img/__init__.py
wata/resources/pcd/000000.bin
wata/resources/pcd/__init__.py
wata-0.1.3.3.dist-info/METADATA
wata-0.1.3.3.dist-info/WHEEL
wata-0.1.3.3.dist-info/top_level.txt
wata-0.1.3.3.dist-info/RECORD
