Metadata-Version: 2.1
Name: wata
Version: 0.1.3.3
Summary: wangtao tools
Home-page: 
Author: wangtao
Author-email: 1083719817@qq.com
Maintainer: wangtao
Maintainer-email: 1083719817@qq.com
License: MIT License
Platform: Linux
Classifier: Development Status :: 3 - Alpha
Classifier: Intended Audience :: Developers
Classifier: Topic :: Software Development :: Build Tools
Classifier: License :: OSI Approved :: MIT License
Classifier: Programming Language :: Python :: 3
Requires-Python: >=3.6
Requires-Dist: numpy
Requires-Dist: PyQt5
Requires-Dist: PyOpenGL
Requires-Dist: pyqtgraph
Requires-Dist: python-lzf
Requires-Dist: matplotlib
Requires-Dist: opencv-python
Requires-Dist: opencv-contrib-python
Requires-Dist: tqdm
Requires-Dist: utm
Requires-Dist: pyyaml
Requires-Dist: vtk
Requires-Dist: scipy
Requires-Dist: tabulate
Requires-Dist: pyquaternion
